alfese/__init__.py
alfese/alfese.py
alfese-1.0.0.dist-info/LICENSE
alfese-1.0.0.dist-info/METADATA
alfese-1.0.0.dist-info/WHEEL
alfese-1.0.0.dist-info/top_level.txt
alfese-1.0.0.dist-info/RECORD
