Metadata-Version: 2.1
Name: alfese
Version: 1.0.0
Summary: Alternative feature selection
Author-email: Jakob Bach <jakob.bach.ka@gmail.com>
Project-URL: Homepage, https://github.com/Jakob-Bach/Alternative-Feature-Selection/tree/main/alfese_package
Project-URL: Issues, https://github.com/Jakob-Bach/Alternative-Feature-Selection/issues
Keywords: feature selection,alternatives,constraints
Classifier: Programming Language :: Python :: 3
Classifier: License :: OSI Approved :: MIT License
Classifier: Operating System :: OS Independent
Requires-Python: >=3.8
License-File: LICENSE
Requires-Dist: numpy >=1.22.3
Requires-Dist: ortools >=9.3.10497
Requires-Dist: pandas >=1.4.1
Requires-Dist: scikit-learn >=1.0.2
